checkers/__init__.py
checkers/board.py
checkers/board_initializer.py
checkers/board_searcher.py
checkers/game.py
checkers/piece.py
imparaai_checkers-1.0.0.dist-info/METADATA
imparaai_checkers-1.0.0.dist-info/RECORD
imparaai_checkers-1.0.0.dist-info/WHEEL
imparaai_checkers-1.0.0.dist-info/top_level.txt
test/__init__.py
test/test_game_over.py
test/test_possible_moves.py
test/test_winner.py
