Metadata-Version: 2.1
Name: imparaai-checkers
Version: 1.0.0
Summary: Library for playing a standard game of checkers/draughts
Home-page: https://github.com/ImparaAI/checkers
Author: ImparaAI
Author-email: author@example.com
License: MIT
Platform: UNKNOWN
Classifier: Programming Language :: Python :: 3
Classifier: License :: OSI Approved :: MIT License
Classifier: Operating System :: OS Independent
